{
    "mission": [
        {
            "monsterList": [
                {
                    "monsterID": 1,
                    "count": 1,
                    "wayID": 1,
                    "rate": 2
                },
                {
                    "monsterID": 1,
                    "count": 1,
                    "wayID": 1,
                    "rate": 2
                }
            ],
            "time": 3
        },
        {
            "monsterList": [
                {
                    "monsterID": 1,
                    "count": 4,
                    "wayID": 2,
                    "rate": 1
                },
                {
                    "monsterID": 1,
                    "count": 4,
                    "wayID": 1,
                    "rate": 1
                },
                {
                    "monsterID": 1,
                    "count": 6,
                    "wayID": 2,
                    "rate": 1
                }
            ],
            "time": 10
        }
    ]
}